{
  "user": [
    {
      "username": "张三",
      "password": "1234",
      "id": 1
    },
    {
      "username": "李四",
      "password": "5678",
      "id": 2
    },
    {
      "username": "王五",
      "password": "12345",
      "id": 3
    }
  ],
  "student": [
    {
      "name": "张三",
      "age": 18,
      "sex": 1,
      "id": 1
    },
    {
      "name": "赵芳",
      "age": 16,
      "sex": 0,
      "id": 3
    },
    {
      "name": "大神",
      "age": 14,
      "sex": 1,
      "id": 5
    },
    {
      "name": "王五",
      "age": 16,
      "sex": 0,
      "id": 9
    },
    {
      "name": "点击",
      "age": "15",
      "sex": "1",
      "id": 12
    },
    {
      "name": "为我",
      "age": 16,
      "sex": 0,
      "id": 15
    },
    {
      "name": "呃呃",
      "age": 16,
      "sex": 0,
      "id": 16
    },
    {
      "name": "里斯",
      "age": 16,
      "sex": 0,
      "id": 21
    },
    {
      "name": "李四",
      "age": 16,
      "sex": 0,
      "id": 22
    }
  ]
}